_cmake/vunit/vunit_defines.svh
//------------------------------------------------------------------------------
//
// vunit_defines.svh - VUnit compatibility macros for Icarus Verilog
//
// This file provides VUnit-compatible macros that work with Icarus Verilog
// in standalone mode (without the VUnit Python runner).
//
// Features:
//   - CHECK_EQUAL, CHECK_TRUE, CHECK_FALSE assertions
//   - TEST_SUITE / TEST_CASE structure
//   - WATCHDOG timeout protection
//   - Exit code file for CMake integration
//   - Automatic test completion and summary
//
//------------------------------------------------------------------------------

`ifndef VUNIT_DEFINES_SVH
`define VUNIT_DEFINES_SVH

//------------------------------------------------------------------------------
// Global test state variables
// These must be declared at module scope before TEST_SUITE
//------------------------------------------------------------------------------

integer __vunit_check_count = 0;
integer __vunit_fail_count = 0;
integer __vunit_test_done = 0;
string  __vunit_current_test = "";

//------------------------------------------------------------------------------
// Exit code file writer
// Writes test result to file for CMake to check
//------------------------------------------------------------------------------

task automatic __vunit_write_result(input integer failed);
    integer fd;
    fd = $fopen("vunit_exit_code.txt", "w");
    if (fd) begin
        $fdisplay(fd, "%0d", failed ? 1 : 0);
        $fclose(fd);
    end
endtask

//------------------------------------------------------------------------------
// Test summary printer
//------------------------------------------------------------------------------

task automatic __vunit_print_summary();
    $display("");
    $display("============================================================");
    $display("                     TEST SUMMARY");
    $display("============================================================");
    $display("  Total Checks : %0d", __vunit_check_count);
    $display("  Failures     : %0d", __vunit_fail_count);
    $display("------------------------------------------------------------");
    if (__vunit_fail_count == 0) begin
        $display("  RESULT: *** PASSED ***");
    end else begin
        $display("  RESULT: *** FAILED ***");
    end
    $display("============================================================");
    $display("");
endtask

//------------------------------------------------------------------------------
// TEST_SUITE - Defines a test suite
//
// Usage:
//   `TEST_SUITE begin
//     `TEST_CASE("test1") begin ... end
//   end
//
// The closing 'end' will trigger test completion.
//------------------------------------------------------------------------------

`define TEST_SUITE \
    initial

//------------------------------------------------------------------------------
// TEST_CASE - Defines a test case
//
// Usage:
//   `TEST_CASE("Test Name") begin
//     // test code
//   end
//------------------------------------------------------------------------------

`define TEST_CASE(test_name) \
    __vunit_current_test = test_name; \
    $display(""); \
    $display("============================================================"); \
    $display("  TEST CASE: %s", test_name); \
    $display("============================================================"); \
    $display("");

//------------------------------------------------------------------------------
// CHECK_EQUAL - Assert equality
//
// Usage:
//   `CHECK_EQUAL(expected, actual)
//------------------------------------------------------------------------------

`define CHECK_EQUAL(expected, actual) \
    begin \
        __vunit_check_count = __vunit_check_count + 1; \
        if ((expected) !== (actual)) begin \
            $display(""); \
            $display("*** ASSERTION FAILED ***"); \
            $display("  CHECK_EQUAL at %s:%0d", `__FILE__, `__LINE__); \
            $display("  Test: %s", __vunit_current_test); \
            $display("  Expected: %0d (0x%0h)", (expected), (expected)); \
            $display("  Actual:   %0d (0x%0h)", (actual), (actual)); \
            $display(""); \
            __vunit_fail_count = __vunit_fail_count + 1; \
        end \
    end

//------------------------------------------------------------------------------
// CHECK_TRUE - Assert condition is true
//------------------------------------------------------------------------------

`define CHECK_TRUE(condition) \
    begin \
        __vunit_check_count = __vunit_check_count + 1; \
        if (!(condition)) begin \
            $display(""); \
            $display("*** ASSERTION FAILED ***"); \
            $display("  CHECK_TRUE at %s:%0d", `__FILE__, `__LINE__); \
            $display("  Test: %s", __vunit_current_test); \
            $display("  Condition was FALSE"); \
            $display(""); \
            __vunit_fail_count = __vunit_fail_count + 1; \
        end \
    end

//------------------------------------------------------------------------------
// CHECK_FALSE - Assert condition is false
//------------------------------------------------------------------------------

`define CHECK_FALSE(condition) \
    begin \
        __vunit_check_count = __vunit_check_count + 1; \
        if (condition) begin \
            $display(""); \
            $display("*** ASSERTION FAILED ***"); \
            $display("  CHECK_FALSE at %s:%0d", `__FILE__, `__LINE__); \
            $display("  Test: %s", __vunit_current_test); \
            $display("  Condition was TRUE"); \
            $display(""); \
            __vunit_fail_count = __vunit_fail_count + 1; \
        end \
    end

//------------------------------------------------------------------------------
// WATCHDOG - Timeout protection
//
// Usage:
//   `WATCHDOG(10000us)
//
// The watchdog monitors the __vunit_test_done flag and terminates
// the simulation with proper cleanup if the test completes or times out.
//------------------------------------------------------------------------------

`define WATCHDOG(timeout) \
    initial begin : __vunit_watchdog_block \
        fork \
            begin : timeout_thread \
                #(timeout); \
                if (!__vunit_test_done) begin \
                    $display(""); \
                    $display("!!!!!!!!!!!!!!!!!!!!!!!!!!!!!!!!!!!!!!!!!!!!!!!!!!!!!!!!!!!!!"); \
                    $display("  WATCHDOG TIMEOUT after %0t", $time); \
                    $display("!!!!!!!!!!!!!!!!!!!!!!!!!!!!!!!!!!!!!!!!!!!!!!!!!!!!!!!!!!!!!"); \
                    __vunit_fail_count = __vunit_fail_count + 1; \
                    __vunit_print_summary(); \
                    __vunit_write_result(1); \
                    $finish; \
                end \
            end \
            begin : completion_thread \
                wait(__vunit_test_done == 1); \
                disable timeout_thread; \
                __vunit_print_summary(); \
                __vunit_write_result(__vunit_fail_count > 0); \
                $finish; \
            end \
        join \
    end

//------------------------------------------------------------------------------
// TEST_DONE - Mark test as complete (call at end of TEST_SUITE)
//
// This triggers the watchdog's completion thread to finish gracefully.
//------------------------------------------------------------------------------

`define TEST_DONE \
    __vunit_test_done = 1

//------------------------------------------------------------------------------
// Compatibility: File/line macros
//------------------------------------------------------------------------------

`ifndef __FILE__
`define __FILE__ "unknown"
`endif

`ifndef __LINE__
`define __LINE__ 0
`endif

`endif // VUNIT_DEFINES_SVH

build/stubs/sync_reg.v
//------------------------------------------------------------------------------
// sync_reg.v - Synchronizer register stub for testing
//
// This is a stub implementation. Replace with actual sync_reg for production.
//------------------------------------------------------------------------------

module sync_reg #(
    parameter WIDTH = 1,
    parameter RST_ST = 0
) (
    input wire clk,
    input wire rst,
    input wire [WIDTH-1:0] din,
    output reg [WIDTH-1:0] dout
);

    reg [WIDTH-1:0] sync_r1;
    reg [WIDTH-1:0] sync_r2;

    always @(posedge clk or posedge rst) begin
        if (rst) begin
            sync_r1 <= RST_ST;
            sync_r2 <= RST_ST;
            dout <= RST_ST;
        end else begin
            sync_r1 <= din;
            sync_r2 <= sync_r1;
            dout <= sync_r2;
        end
    end

endmodule

async_fifo/rtl/async_fifo.v
//-----------------------------------------------------------------------------
//
// async_fifo.v - FIFO with separate clocks for read and write ports
//
// Copyright (c) 2019 
//
// Contact: 
//
// ----------------------------------------------------------------------------

module async_fifo #(
    parameter DATA_WIDTH = 8,
    parameter ADDR_WIDTH = 12,
    parameter RESERVE = 0
) (   input rst

    , input wr_clk
    , input wr_en
    , input [DATA_WIDTH-1:0] wr_data
    , output full

    , input  rd_clk
    , input  rd_en
    , output reg [DATA_WIDTH-1:0] rd_data
    , output empty
    , output has_data
);

    wire rst_sw, rst_sr;

    sync_reg #( .WIDTH(1), .RST_ST(1)
    ) SYNC_WR ( .clk ( wr_clk ), .rst ( rst )
        , .din   ( rst   )
        , .dout  ( rst_sw  )
    );

    sync_reg #( .WIDTH(1), .RST_ST(1)
    ) SYNC_RR ( .clk ( rd_clk ), .rst ( rst )
        , .din   ( rst   )
        , .dout  ( rst_sr  )
    );

    localparam DEPTH = 2**ADDR_WIDTH;

    localparam RAM_TYPE = (ADDR_WIDTH > 6) ? "BLOCK" : "DISTRIBUTED";
        (* RAM_STYLE = RAM_TYPE *) reg [DATA_WIDTH-1:0] ram[DEPTH-1:0];



    reg [ADDR_WIDTH:0] wr_ptr;
    reg [ADDR_WIDTH:0] rd_ptr;

    wire [ADDR_WIDTH:0] occup;
    wire [ADDR_WIDTH+1:0] space;

    wire [ADDR_WIDTH:0] wr_ptr_gray;
    wire [ADDR_WIDTH:0] rd_ptr_gray;

    reg  [ADDR_WIDTH:0] wr_ptr_gray_r;
    reg  [ADDR_WIDTH:0] rd_ptr_gray_r;

    wire [ADDR_WIDTH:0] wr_ptr_dec;
    wire [ADDR_WIDTH:0] rd_ptr_dec;

    reg [ADDR_WIDTH:0] wr_ptr_sync;
    reg [ADDR_WIDTH:0] rd_ptr_sync;

    reg [ADDR_WIDTH:0] wr_ptr_s1;
    reg [ADDR_WIDTH:0] rd_ptr_s1;

    reg [ADDR_WIDTH:0] wr_ptr_s2;
    reg [ADDR_WIDTH:0] rd_ptr_s2;

    reg [2:0] wr_rst_cnt;
    reg [2:0] rd_rst_cnt;

    reg wr_rst;
    reg rd_rst;
    reg not_empty;

    wire full_i;

    function[ADDR_WIDTH:0] binary2gray;
        input[ADDR_WIDTH:0] input_value;
        integer i;
        begin
            binary2gray[ADDR_WIDTH] = input_value[ADDR_WIDTH];
            for (i=0; i<ADDR_WIDTH; i = i+1)
                binary2gray[i] = input_value[i] ^ input_value[i + 1];
        end
    endfunction

    function[ADDR_WIDTH:0] gray2binary;
        input[ADDR_WIDTH:0] input_value;
        integer i;
        begin
            gray2binary[ADDR_WIDTH] = input_value[ADDR_WIDTH];
            for (i=ADDR_WIDTH; i>0; i=i-1)
                gray2binary[i-1] = input_value[i-1] ^ gray2binary[i];
        end
    endfunction

    assign wr_ptr_gray = binary2gray(wr_ptr);
    assign rd_ptr_gray = binary2gray(rd_ptr);

    assign wr_ptr_dec = gray2binary(wr_ptr_s2);
    assign rd_ptr_dec = gray2binary(rd_ptr_s2);

     always @(posedge rd_clk) begin
       if (rd_rst) begin
        wr_ptr_s1 <= 'b0;
        wr_ptr_s2 <= 'b0;
        wr_ptr_sync <= 'b0;
        rd_ptr_gray_r <= 'b0;
      end else begin
        rd_ptr_gray_r <= rd_ptr_gray;
        wr_ptr_s1 <= wr_ptr_gray_r;
        wr_ptr_s2 <= wr_ptr_s1;
        wr_ptr_sync <= wr_ptr_dec;
      end
    end

    always @(posedge wr_clk) begin
      if (wr_rst) begin
        rd_ptr_s1 <= 'b0;
        rd_ptr_s2 <= 'b0;
        rd_ptr_sync <= 'b0;
        wr_ptr_gray_r <= 'b0;
      end else begin
        wr_ptr_gray_r <= wr_ptr_gray;
        rd_ptr_s1 <= rd_ptr_gray_r;
        rd_ptr_s2 <= rd_ptr_s1;
        rd_ptr_sync <= rd_ptr_dec;
      end
    end

    assign empty = (rd_ptr == wr_ptr_sync) ? 1'b1 : rd_rst;
    assign has_data = (rd_ptr == wr_ptr_sync) ? 1'b0 : (~rd_rst);

    assign occup = (wr_ptr - rd_ptr_sync);
    assign space =  DEPTH - {1'b0, occup};

    reg    full_reg;
    assign full_i  = ((wr_ptr[ADDR_WIDTH-1:0] == rd_ptr_sync[ADDR_WIDTH-1:0])
                      && (wr_ptr[ADDR_WIDTH] != rd_ptr_sync[ADDR_WIDTH])) ? 1'b1 : 1'b0;
    /* verilator lint_off WIDTH */
    assign full    = (space <= RESERVE) ? 1'b1 : full_reg | wr_rst;
    /* verilator lint_on WIDTH */

    always @(posedge wr_clk) begin
      if(wr_rst) begin
        full_reg <= 1'b1;
      end else begin
        full_reg <= 1'b0;
      end
    end


    always @(posedge wr_clk ) begin
      if (rst_sw) begin
        wr_rst_cnt <= 3'd7;
        wr_rst <= 1'b1;
      end else begin
        if (|wr_rst_cnt) begin
          wr_rst_cnt <= wr_rst_cnt - 1'b1;
          wr_rst <= 1'b1;
        end else begin
          wr_rst <= 1'b0;
        end
      end
    end

    always @(posedge wr_clk) begin
      if (wr_rst) begin
        wr_ptr <= 'b0;
      end else if (wr_en && !full_i) begin
        wr_ptr <= wr_ptr + 1'b1;
      end
    end

    wire wr_en_i = wr_en & ~full_i;

    always @(posedge wr_clk) begin
      if (wr_en_i) begin
          ram[wr_ptr[ADDR_WIDTH-1:0]] <= wr_data;
      end
    end

    always @(posedge rd_clk ) begin
        if (rst_sr) begin
            rd_rst_cnt <= 3'd7;
            rd_rst <= 1'b1;
        end else begin
            if (|rd_rst_cnt) begin
                rd_rst_cnt <= rd_rst_cnt - 1'b1;
                rd_rst <= 1'b1;
            end else begin
                rd_rst <= 1'b0;
            end
        end
    end

    always @(posedge rd_clk) begin
        if (rd_rst) begin
            rd_ptr <= 'b0;
        end else if (rd_en && !empty) begin
            rd_ptr <= rd_ptr + 1'b1;
        end
    end

    wire rd_en_i = rd_en && !empty;

    always @(posedge rd_clk) begin
      if (rd_en_i) begin
         rd_data <= ram[rd_ptr[ADDR_WIDTH-1:0]];
      end
    end

endmodule

src/cores/async_fifo/rtl/async_fifo_fwft.v
//-----------------------------------------------------------------------------
//
// async_fifo_fwft.v - FIFO with separate clocks for read and write ports
//                      First word fall through version
//
// Copyright (c) 2019 
//
// Contact: 
//
// ----------------------------------------------------------------------------

module async_fifo_fwft #(
    parameter DATA_WIDTH = 8,
    parameter ADDR_WIDTH = 12,
    parameter RESERVE = 12'd0
) (   input  rst
    , input  wr_clk
    , input  wr_en
    , output full
    , input  [DATA_WIDTH-1:0] wr_data

    , input  rd_clk
    , input  rd_en
    , output empty
    , output has_data
    , output [DATA_WIDTH-1:0] rd_data
);

  wire                  rd_en_i;
  reg                   rd_en_i_d1;
  wire [DATA_WIDTH-1:0] rd_data_i;
  wire                  empty_i;
  wire                  has_data_i;
  reg                   data_in_reg;

  async_fifo #(
        .DATA_WIDTH(DATA_WIDTH)
      , .ADDR_WIDTH(ADDR_WIDTH)
      , .RESERVE(RESERVE)
  ) FIFO_INST (
      .rst(rst)

      , .wr_clk(wr_clk)
      , .wr_en(wr_en)
      , .wr_data(wr_data)
      , .full(full)

      , .rd_clk(rd_clk)
      , .rd_en(rd_en_i)
      , .rd_data(rd_data_i)
      , .empty(empty_i)
      , .has_data(has_data_i)
  );

  assign rd_en_i =  (has_data_i & ~data_in_reg)
                  | (has_data_i & rd_en);

  reg [2:0] rd_rst_cnt;
  reg rd_rst;

  always @(posedge rd_clk or posedge rst) begin
    if (rst) begin
      rd_rst_cnt <= 3'd7;
      rd_rst <= 1'b1;
    end else begin
      if (|rd_rst_cnt) begin
        rd_rst_cnt <= rd_rst_cnt - 1'b1;
        rd_rst <= 1'b1;
      end else begin
        rd_rst <= 1'b0;
      end
    end
  end

  always @(posedge rd_clk) begin
    if(rd_rst) begin
      data_in_reg <= 1'b0;
    end else begin
      if (rd_en) begin
        data_in_reg <= has_data_i;
      end else if (rd_en_i) begin
        data_in_reg <= 1'b1;
      end
    end
  end

  assign has_data = data_in_reg;
  assign empty = ~data_in_reg;

  assign rd_data = rd_data_i;

endmodule

src/cores/async_fifo/test/write_past_fwft/async_fifo_fwft_writepast_tb.sv
`timescale 1ps/1ps
`include "vunit_defines.svh"

module async_fifo_fwft_writepast_tb;

logic rst, wr_clk = 1'b0, rd_clk = 1'b0;
logic wr_allow, wr_allow_r, wr_expect, wr_expect_r, rd_allow, rd_allow_r;
wire  full, empty, has_data, rd_en, wr_en;
logic [7:0] wr_data;
wire  [7:0] rd_data;
reg         rd_en_d1;

logic [7:0] data_queue[$];
logic [7:0] data_rec;
logic [7:0] data_rec_out;

integer write_count = 0;

always begin
  #10000;
  rd_clk <= !rd_clk;
end

always begin
  #10000;
  wr_clk <= !wr_clk;
end

async_fifo_fwft #(
      .DATA_WIDTH( 8 )
    , .ADDR_WIDTH( 4 )
    , .RESERVE( 8 )
) DUT (   .rst      ( rst     )
        , .wr_clk   ( wr_clk  )
        , .wr_en    ( wr_en   )
        , .full     ( full    )
        , .wr_data  ( wr_data )

        , .rd_clk   ( rd_clk   )
        , .rd_en    ( rd_en    )
        , .empty    ( empty    )
        , .has_data ( has_data )
        , .rd_data  ( rd_data  )
);

assign rd_en = rd_allow_r & has_data;
assign wr_en = wr_allow_r;

always @(posedge wr_clk) begin
  wr_allow_r <= wr_allow;
  wr_expect_r <= wr_expect;
  if( rst ) begin
    wr_data <= 8'd0;
  end else if( wr_en ) begin
    $display( "Input data was %d  while %s", wr_data, full ? "FULL":"NOT full" );
    data_rec = wr_data;
    if(wr_expect_r) begin
      data_queue.push_back(data_rec);
    end
    write_count = write_count + 1;
    wr_data <= wr_data + 1;
  end
end

always @(posedge rd_clk) begin
  rd_en_d1 <= rd_en;
  rd_allow_r <= rd_allow;
  if( rd_en ) begin
    if( data_queue.size() == 0) begin
      $display( "NO DATA IN RECORD QUEUE" );
      `CHECK_EQUAL( 8'hXX, rd_data );
    end else begin
      data_rec_out = data_queue.pop_front();
      $display( "Output data was %d, %s", rd_data, data_rec_out == rd_data ? "MATCH" : "NO MATCH!!!!!!!" );
      `CHECK_EQUAL( data_rec_out, rd_data );
    end
  end
end

`TEST_SUITE begin

  `TEST_CASE("Write-Past") begin
    $dumpfile("test_case_1.vcd");
    $dumpvars();

    wr_allow <= 1'b0;
    rd_allow <= 1'b0;
    wr_expect <= 1'b0;

    rst <= 1'b1;
    repeat(20) begin
      @(posedge wr_clk);
    end
    rst <= 1'b0;
    repeat(20) begin
      @(posedge wr_clk);
    end


    $display( "----STARTING THE TESTBENCH-----" );
    wr_allow <= 1'b1;
    wr_expect <= 1'b1;
    repeat(17) begin
      @(posedge wr_clk);
    end
    wr_expect <= 1'b0;
    repeat(3) begin
      @(posedge wr_clk);
    end
    wr_allow <= 1'b0;

    repeat(20) begin
      @(posedge wr_clk);
    end
    rd_allow <= 1'b1;

    repeat(100) begin
      @(posedge wr_clk);
    end
    rd_allow <= 1'b0;

    wr_allow <= 1'b1;
    wr_expect <= 1'b1;
    repeat(17) begin
      @(posedge wr_clk);
    end
    wr_expect <= 1'b0;
    repeat(3) begin
      @(posedge wr_clk);
    end
    wr_allow <= 1'b0;

    repeat(20) begin
      @(posedge wr_clk);
    end
    rd_allow <= 1'b1;

    repeat(100) begin
      @(posedge wr_clk);
    end



    #(64'd5000000);
    `CHECK_EQUAL( 1'b1, 1'b1 );
  end

end

`WATCHDOG(10000us);

endmodule

build/test_case_1.vcd
$date
	Thu Dec 11 15:30:26 2025
$end
$version
	Icarus Verilog
$end
$timescale
	1ps
$end
$scope module async_fifo_fwft_writepast_tb $end
$var wire 1 ! rd_en $end
$var wire 1 " wr_en $end
$var wire 8 # rd_data [7:0] $end
$var wire 1 $ has_data $end
$var wire 1 % full $end
$var wire 1 & empty $end
$var reg 8 ' data_rec [7:0] $end
$var reg 8 ( data_rec_out [7:0] $end
$var reg 1 ) rd_allow $end
$var reg 1 * rd_allow_r $end
$var reg 1 + rd_clk $end
$var reg 1 , rd_en_d1 $end
$var reg 1 - rst $end
$var reg 1 . wr_allow $end
$var reg 1 " wr_allow_r $end
$var reg 1 / wr_clk $end
$var reg 8 0 wr_data [7:0] $end
$var reg 1 1 wr_expect $end
$var reg 1 2 wr_expect_r $end
$var integer 32 3 write_count [31:0] $end
$scope module DUT $end
$var wire 1 & empty $end
$var wire 1 $ has_data $end
$var wire 1 + rd_clk $end
$var wire 8 4 rd_data [7:0] $end
$var wire 1 ! rd_en $end
$var wire 1 5 rd_en_i $end
$var wire 1 - rst $end
$var wire 1 / wr_clk $end
$var wire 8 6 wr_data [7:0] $end
$var wire 1 " wr_en $end
$var wire 8 7 rd_data_i [7:0] $end
$var wire 1 8 has_data_i $end
$var wire 1 % full $end
$var wire 1 9 empty_i $end
$var parameter 32 : ADDR_WIDTH $end
$var parameter 32 ; DATA_WIDTH $end
$var parameter 32 < RESERVE $end
$var reg 1 = data_in_reg $end
$var reg 1 > rd_rst $end
$var reg 3 ? rd_rst_cnt [2:0] $end
$scope module FIFO_INST $end
$var wire 1 + rd_clk $end
$var wire 1 5 rd_en $end
$var wire 1 @ rd_en_i $end
$var wire 1 - rst $end
$var wire 1 / wr_clk $end
$var wire 8 A wr_data [7:0] $end
$var wire 1 " wr_en $end
$var wire 1 B wr_en_i $end
$var wire 5 C wr_ptr_gray [4:0] $end
$var wire 5 D wr_ptr_dec [4:0] $end
$var wire 6 E space [5:0] $end
$var wire 1 F rst_sw $end
$var wire 1 G rst_sr $end
$var wire 5 H rd_ptr_gray [4:0] $end
$var wire 5 I rd_ptr_dec [4:0] $end
$var wire 5 J occup [4:0] $end
$var wire 1 8 has_data $end
$var wire 1 K full_i $end
$var wire 1 % full $end
$var wire 1 9 empty $end
$var parameter 32 L ADDR_WIDTH $end
$var parameter 32 M DATA_WIDTH $end
$var parameter 32 N DEPTH $end
$var parameter 88 O RAM_TYPE $end
$var parameter 32 P RESERVE $end
$var reg 1 Q full_reg $end
$var reg 8 R rd_data [7:0] $end
$var reg 5 S rd_ptr [4:0] $end
$var reg 5 T rd_ptr_gray_r [4:0] $end
$var reg 5 U rd_ptr_s1 [4:0] $end
$var reg 5 V rd_ptr_s2 [4:0] $end
$var reg 5 W rd_ptr_sync [4:0] $end
$var reg 1 X rd_rst $end
$var reg 3 Y rd_rst_cnt [2:0] $end
$var reg 5 Z wr_ptr [4:0] $end
$var reg 5 [ wr_ptr_gray_r [4:0] $end
$var reg 5 \ wr_ptr_s1 [4:0] $end
$var reg 5 ] wr_ptr_s2 [4:0] $end
$var reg 5 ^ wr_ptr_sync [4:0] $end
$var reg 1 _ wr_rst $end
$var reg 3 ` wr_rst_cnt [2:0] $end
$scope function binary2gray $end
$var reg 5 a input_value [4:0] $end
$var integer 32 b i [31:0] $end
$upscope $end
$scope function gray2binary $end
$var reg 5 c input_value [4:0] $end
$var integer 32 d i [31:0] $end
$upscope $end
$scope module SYNC_RR $end
$var wire 1 + clk $end
$var wire 1 - din $end
$var wire 1 - rst $end
$var parameter 32 e RST_ST $end
$var parameter 32 f WIDTH $end
$var reg 1 G dout $end
$var reg 1 g sync_r1 $end
$var reg 1 h sync_r2 $end
$upscope $end
$scope module SYNC_WR $end
$var wire 1 / clk $end
$var wire 1 - din $end
$var wire 1 - rst $end
$var parameter 32 i RST_ST $end
$var parameter 32 j WIDTH $end
$var reg 1 F dout $end
$var reg 1 k sync_r1 $end
$var reg 1 l sync_r2 $end
$upscope $end
$upscope $end
$upscope $end
$scope begin __vunit_watchdog_block $end
$scope begin completion_thread $end
$upscope $end
$scope begin timeout_thread $end
$upscope $end
$upscope $end
$upscope $end
$enddefinitions $end
$comment Show the parameter values. $end
$dumpall
b1 j
b1 i
b1 f
b1 e
b1000 P
b100010001001001010100110101010001010010010010010100001001010101010101000100010101000100 O
b10000 N
b1000 M
b100 L
b1000 <
b1000 ;
b100 :
$end
#0
$dumpvars
1l
1k
1h
1g
b0 d
bx c
b100 b
bx a
bx `
x_
bx ^
bx ]
bx \
bx [
bx Z
bx Y
xX
bx W
bx V
bx U
bx T
bx S
bx R
xQ
xK
bx J
bx I
bx H
1G
1F
bx E
bx D
bx C
xB
bx A
x@
b111 ?
1>
x=
x9
x8
bx 7
bx 6
x5
bx 4
b0 3
x2
01
bx 0
0/
0.
1-
x,
0+
x*
0)
bx (
bx '
x&
x%
x$
bx #
x"
x!
$end
#10000
05
1%
0@
08
0B
19
1&
0!
0Q
1_
b111 `
b0 0
b0 6
b0 A
02
0"
1X
b111 Y
0$
0=
0*
1/
1+
#20000
0/
0+
#30000
0K
b0 C
b10000 E
b0 I
b0 H
b100 b
b0 a
b0 D
b0 d
b0 c
b0 J
b0 Z
1Q
b0 [
b0 W
b0 V
b0 U
0,
b0 S
b0 T
b0 ^
b0 ]
b0 \
1/
1+
#40000
0/
0+
#50000
1/
1+
#60000
0/
0+
#70000
1/
1+
#80000
0/
0+
#90000
1/
1+
#100000
0/
0+
#110000
1/
1+
#120000
0/
0+
#130000
1/
1+
#140000
0/
0+
#150000
1/
1+
#160000
0/
0+
#170000
1/
1+
#180000
0/
0+
#190000
1/
1+
#200000
0/
0+
#210000
1/
1+
#220000
0/
0+
#230000
1/
1+
#240000
0/
0+
#250000
1/
1+
#260000
0/
0+
#270000
1/
1+
#280000
0/
0+
#290000
1/
1+
#300000
0/
0+
#310000
1/
1+
#320000
0/
0+
#330000
1/
1+
#340000
0/
0+
#350000
1/
1+
#360000
0/
0+
#370000
1/
1+
#380000
0/
0+
#390000
0-
1/
1+
#400000
0/
0+
#410000
0k
b110 ?
0g
1/
1+
#420000
0/
0+
#430000
0l
0h
b101 ?
1/
1+
#440000
0/
0+
#450000
0F
b100 ?
0G
1/
1+
#460000
0/
0+
#470000
b110 `
b11 ?
b110 Y
1/
1+
#480000
0/
0+
#490000
b101 `
b10 ?
b101 Y
1/
1+
#500000
0/
0+
#510000
b100 `
b1 ?
b100 Y
1/
1+
#520000
0/
0+
#530000
b11 `
b0 ?
b11 Y
1/
1+
#540000
0/
0+
#550000
b10 `
0>
b10 Y
1/
1+
#560000
0/
0+
#570000
b1 `
b1 Y
1/
1+
#580000
0/
0+
#590000
b0 `
b0 Y
1/
1+
#600000
0/
0+
#610000
0_
0X
1/
1+
#620000
0/
0+
#630000
0%
0Q
1/
1+
#640000
0/
0+
#650000
1/
1+
#660000
0/
0+
#670000
1/
1+
#680000
0/
0+
#690000
1/
1+
#700000
0/
0+
#710000
1/
1+
#720000
0/
0+
#730000
1/
1+
#740000
0/
0+
#750000
1/
1+
#760000
0/
0+
#770000
1/
1+
#780000
0/
0+
#790000
11
1.
1/
1+
#800000
0/
0+
#810000
1B
12
1"
1/
1+
#820000
0/
0+
#830000
b1 C
b100 b
b1 a
b1111 E
b1 0
b1 6
b1 A
b1 J
b1 Z
b1 3
b0 '
1/
1+
#840000
0/
0+
#850000
b11 C
b100 b
b10 a
b1110 E
b1 [
b10 J
b10 Z
b10 0
b10 6
b10 A
b10 3
b1 '
1/
1+
#860000
0/
0+
#870000
b10 C
b100 b
b11 a
b1101 E
b11 0
b11 6
b11 A
b11 J
b11 Z
b11 [
b1 \
b11 3
b10 '
1/
1+
#880000
0/
0+
#890000
b110 C
b100 b
b100 a
b1100 E
b1 D
b0 d
b1 c
b10 [
b100 J
b100 Z
b100 0
b100 6
b100 A
b1 ]
b11 \
b100 3
b11 '
1/
1+
#900000
0/
0+
#910000
1@
15
b111 C
b100 b
b101 a
b1011 E
09
18
b10 D
b0 d
b11 c
b101 0
b101 6
b101 A
b101 J
b101 Z
b110 [
b1 ^
b11 ]
b10 \
b101 3
b100 '
1/
1+
#920000
0/
0+
#930000
0@
05
b101 C
b1010 E
b11 D
b0 d
b10 c
b1 H
b100 b
b110 a
0&
b111 [
b110 J
b110 Z
b110 0
b110 6
b110 A
b10 ^
b10 ]
b110 \
b1 S
b0 #
b0 4
b0 7
b0 R
1$
1=
b110 3
b101 '
1/
1+
#940000
0/
0+
#950000
b100 C
b100 b
b111 a
b1001 E
b100 D
b0 d
b110 c
b111 0
b111 6
b111 A
b111 J
b111 Z
b101 [
b11 ^
b110 ]
b111 \
b1 T
b111 3
b110 '
1/
1+
#960000
0/
0+
#970000
1%
b1100 C
b100 b
b1000 a
b1000 E
b101 D
b0 d
b111 c
b1 U
b100 [
b1000 J
b1000 Z
b1000 0
b1000 6
b1000 A
b100 ^
b111 ]
b101 \
b1000 3
b111 '
1/
1+
#980000
0/
0+
#990000
b1101 C
b100 b
b1001 a
b111 E
b1 I
b110 D
b0 d
b1 c
b1001 0
b1001 6
b1001 A
b1001 J
b1001 Z
b1 V
b1100 [
b101 ^
b101 ]
b100 \
b1001 3
b1000 '
1/
1+
#1000000
0/
0+
#1010000
b1111 C
b100 b
b1010 a
b111 D
b0 d
b100 c
b1 W
b1101 [
b1001 J
b1010 Z
b1010 0
b1010 6
b1010 A
b110 ^
b100 ]
b1100 \
b1010 3
b1001 '
1/
1+
#1020000
0/
0+
#1030000
b1110 C
b100 b
b1011 a
b110 E
b1000 D
b0 d
b1100 c
b1011 0
b1011 6
b1011 A
b1010 J
b1011 Z
b1111 [
b111 ^
b1100 ]
b1101 \
b1011 3
b1010 '
1/
1+
#1040000
0/
0+
#1050000
b1010 C
b100 b
b1100 a
b101 E
b1001 D
b0 d
b1101 c
b1110 [
b1011 J
b1100 Z
b1100 0
b1100 6
b1100 A
b1000 ^
b1101 ]
b1111 \
b1100 3
b1011 '
1/
1+
#1060000
0/
0+
#1070000
b1011 C
b100 b
b1101 a
b100 E
b1010 D
b0 d
b1111 c
b1101 0
b1101 6
b1101 A
b1100 J
b1101 Z
b1010 [
b1001 ^
b1111 ]
b1110 \
b1101 3
b1100 '
1/
1+
#1080000
0/
0+
#1090000
b1001 C
b100 b
b1110 a
b11 E
b1011 D
b0 d
b1110 c
b1011 [
b1101 J
b1110 Z
b1110 0
b1110 6
b1110 A
b1010 ^
b1110 ]
b1010 \
b1110 3
b1101 '
1/
1+
#1100000
0/
0+
#1110000
b1000 C
b100 b
b1111 a
b10 E
b1100 D
b0 d
b1010 c
b1111 0
b1111 6
b1111 A
b1110 J
b1111 Z
b1001 [
b1011 ^
b1010 ]
b1011 \
b1111 3
b1110 '
1/
1+
#1120000
0/
0+
#1130000
b11000 C
b100 b
b10000 a
b1 E
b1101 D
b0 d
b1011 c
b1000 [
b1111 J
b10000 Z
b10000 0
b10000 6
b10000 A
01
b1100 ^
b1011 ]
b1001 \
b10000 3
b1111 '
1/
1+
#1140000
0/
0+
#1150000
0B
1K
b11001 C
b100 b
b10001 a
b0 E
b1110 D
b0 d
b1001 c
b10001 0
b10001 6
b10001 A
02
b10000 J
b10001 Z
b11000 [
b1101 ^
b1001 ]
b1000 \
b10001 3
b10000 '
1/
1+
#1160000
0/
0+
#1170000
b1111 D
b0 d
b1000 c
b11001 [
b10010 0
b10010 6
b10010 A
b1110 ^
b1000 ]
b11000 \
b10010 3
b10001 '
1/
1+
#1180000
0/
0+
#1190000
b10000 D
b0 d
b11000 c
0.
b10011 0
b10011 6
b10011 A
b1111 ^
b11000 ]
b11001 \
b10011 3
b10010 '
1/
1+
#1200000
0/
0+
#1210000
b10001 D
b0 d
b11001 c
b10100 0
b10100 6
b10100 A
0"
b10000 ^
b11001 ]
b10100 3
b10011 '
1/
1+
#1220000
0/
0+
#1230000
b10001 ^
1/
1+
#1240000
0/
0+
#1250000
1/
1+
#1260000
0/
0+
#1270000
1/
1+
#1280000
0/
0+
#1290000
1/
1+
#1300000
0/
0+
#1310000
1/
1+
#1320000
0/
0+
#1330000
1/
1+
#1340000
0/
0+
